cool_lib/__init__.py
cool_lib/__main__.py
cool_lib/a.py
cool_lib/b.py
cool_lib/data/some-data.txt
tests/getting_started_test.py
cool_lib_forked_1-1.9.2.dist-info/METADATA
cool_lib_forked_1-1.9.2.dist-info/WHEEL
cool_lib_forked_1-1.9.2.dist-info/entry_points.txt
cool_lib_forked_1-1.9.2.dist-info/top_level.txt
cool_lib_forked_1-1.9.2.dist-info/RECORD
